autopalette/__init__.py
autopalette/autoformat.py
autopalette/colormatch.py
autopalette/colortrans.py
autopalette/palette.py
autopalette/render.py
autopalette/theme.py
autopalette/utils.py
autopalette-0.1.0.post1.dist-info/METADATA
autopalette-0.1.0.post1.dist-info/RECORD
autopalette-0.1.0.post1.dist-info/WHEEL
autopalette-0.1.0.post1.dist-info/top_level.txt
