Metadata-Version: 2.1
Name: autopalette
Version: 0.1.0-1
Summary: Terminal palettes and themes, without tears.
Home-page: https://github.com/hiway/autopalette
Author: Harshad Sharma
Author-email: harshad@sharma.io
License: BSD License
Keywords: terminal,color,theme,palette
Platform: UNKNOWN
Classifier: Environment :: Console
Classifier: Intended Audience :: Developers
Classifier: License :: OSI Approved :: BSD License
Classifier: Operating System :: POSIX
Classifier: Operating System :: POSIX :: BSD
Classifier: Operating System :: POSIX :: BSD :: FreeBSD
Classifier: Operating System :: POSIX :: Linux
Classifier: Operating System :: Unix
Classifier: Programming Language :: Python
Classifier: Programming Language :: Python :: 3.6
Classifier: Programming Language :: Python :: 3.7
Classifier: Programming Language :: Python :: 3 :: Only
Classifier: Programming Language :: Python :: Implementation :: CPython
Classifier: Topic :: Terminals
Classifier: Topic :: Software Development
Classifier: Topic :: Software Development :: User Interfaces
Classifier: Topic :: Utilities
Requires-Dist: colorhash (>=1.0.2)
Requires-Dist: colour (>=0.1.5)
Requires-Dist: kdtree (>=0.16)
Requires-Dist: sty (>=1.0.0b6)
Requires-Dist: emoji2text
Requires-Dist: ftfy
